LICENSE.md
MANIFEST.in
README.md
nest.py
setup.py
nest_thermostat/__init__.py
nest_thermostat.egg-info/PKG-INFO
nest_thermostat.egg-info/SOURCES.txt
nest_thermostat.egg-info/dependency_links.txt
nest_thermostat.egg-info/requires.txt
nest_thermostat.egg-info/top_level.txt