Metadata-Version: 1.0
Name: nest-thermostat
Version: 1.2
Summary: Python API and command line tool for talking to the Nest™ Thermostat
Home-page: https://github.com/FiloSottile/nest_thermostat/
Author: Filippo Valsorda
Author-email: hi@filippo.io
License: UNKNOWN
Platform: UNKNOWN
